alfred3/__init__.py
alfred3/_core.py
alfred3/_helper.py
alfred3/_version.py
alfred3/admin.py
alfred3/alfredlog.py
alfred3/config.py
alfred3/data_manager.py
alfred3/exceptions.py
alfred3/experiment.py
alfred3/export.py
alfred3/localserver.py
alfred3/messages.py
alfred3/page.py
alfred3/quota.py
alfred3/randomizer.py
alfred3/run.py
alfred3/saving_agent.py
alfred3/section.py
alfred3/testutil.py
alfred3/ui_controller.py
alfred3/util.py
alfred3/cli/__init__.py
alfred3/cli/extract.py
alfred3/cli/run_exp.py
alfred3/cli/template_exp.py
alfred3/compatibility/__init__.py
alfred3/compatibility/condition.py
alfred3/element/__init__.py
alfred3/element/action.py
alfred3/element/core.py
alfred3/element/display.py
alfred3/element/input.py
alfred3/element/misc.py
alfred3/element/templates/html/ActionButtonElement.html.j2
alfred3/element/templates/html/AlertElement.html.j2
alfred3/element/templates/html/AudioElement.html.j2
alfred3/element/templates/html/Card.html.j2
alfred3/element/templates/html/ChoiceButtons.html.j2
alfred3/element/templates/html/ChoiceElement.html.j2
alfred3/element/templates/html/DateEntryElement.html.j2
alfred3/element/templates/html/Element.html.j2
alfred3/element/templates/html/EmptyElement.html.j2
alfred3/element/templates/html/HiddenInputElement.html.j2
alfred3/element/templates/html/ImageElement.html.j2
alfred3/element/templates/html/LabelledElement.html.j2
alfred3/element/templates/html/PasswordEntry.html.j2
alfred3/element/templates/html/ProgressBarElement.html.j2
alfred3/element/templates/html/RangeInputElement.html.j2
alfred3/element/templates/html/Row.html.j2
alfred3/element/templates/html/SelectElement.html.j2
alfred3/element/templates/html/TextAreaElement.html.j2
alfred3/element/templates/html/TextElement.html.j2
alfred3/element/templates/html/TextEntryElement.html.j2
alfred3/element/templates/html/TimeEntryElement.html.j2
alfred3/element/templates/html/VideoElement.html.j2
alfred3/element/templates/js/actionbutton.js.j2
alfred3-3.0.2.dist-info/METADATA
alfred3-3.0.2.dist-info/WHEEL
alfred3-3.0.2.dist-info/entry_points.txt
alfred3-3.0.2.dist-info/RECORD
