Metadata-Version: 2.4
Name: alfred3
Version: 3.0.2
Summary: A library for rapid development of dynamic and interactive online experiments in the social sciences.
Project-URL: Homepage, https://github.com/ctreffe/alfred
Project-URL: Documentation, https://alfredo3.psych.bio.uni-goettingen.de/docs/index.html
Project-URL: Repository, https://github.com/ctreffe/alfred
Author: Christian Treffenstädt, Johannes Brachem, Paul Wiemann
License-Expression: MIT
Keywords: social science,web experiment
Classifier: Intended Audience :: Science/Research
Classifier: License :: OSI Approved :: MIT License
Classifier: Programming Language :: Python :: 3
Classifier: Programming Language :: Python :: 3.13
Requires-Python: >=3.13
Requires-Dist: bleach>=3.3
Requires-Dist: click>=7.1
Requires-Dist: cmarkgfm>=0.5
Requires-Dist: cryptography>=3.4
Requires-Dist: emoji<=1.6.3,>=1.2
Requires-Dist: flask>=1.1
Requires-Dist: jinja2>=2.11
Requires-Dist: mongomock
Requires-Dist: pymongo>=3.10
Requires-Dist: pyyaml>=6.0
Requires-Dist: requests>=2.25
Requires-Dist: thesmuggler>=1.0
